simplewebdavclient/__init__.py
simplewebdavclient/checkers.py
simplewebdavclient/exceptions.py
simplewebdavclient/simplewebdavclient.py
simplewebdavclient-1.0.2.dist-info/LICENSE
simplewebdavclient-1.0.2.dist-info/METADATA
simplewebdavclient-1.0.2.dist-info/WHEEL
simplewebdavclient-1.0.2.dist-info/top_level.txt
simplewebdavclient-1.0.2.dist-info/RECORD
