Metadata-Version: 2.1
Name: simplewebdavclient
Version: 1.0.2
Summary: This is a library used to make WebDav Client Connections simple.
Home-page: https://simplewebdavclient.readthedocs.io
Author: Benjamin P. Trachtenberg
Author-email: e_ben_75-python@yahoo.com
License: MIT
Project-URL: Documentation, https://simplewebdavclient.readthedocs.io/en/latest/
Project-URL: Source, https://github.com/btr1975/simplewebdavclient
Project-URL: Tracker, https://github.com/btr1975/simplewebdavclient/issues
Keywords: webdav simple
Platform: UNKNOWN
Classifier: Development Status :: 5 - Production/Stable
Classifier: License :: OSI Approved :: MIT License
Classifier: Intended Audience :: Developers
Classifier: Natural Language :: English
Classifier: Operating System :: MacOS :: MacOS X
Classifier: Operating System :: POSIX
Classifier: Operating System :: POSIX :: BSD
Classifier: Operating System :: POSIX :: Linux
Classifier: Operating System :: Microsoft :: Windows
Classifier: Programming Language :: Python :: 3
Classifier: Programming Language :: Python :: 3 :: Only
Classifier: Programming Language :: Python :: 3.5
Classifier: Programming Language :: Python :: 3.6
Classifier: Programming Language :: Python :: 3.7
Classifier: Programming Language :: Python :: 3.8
Requires-Python: ~=3.3
Requires-Dist: requests (==2.23.0)
